pycapsule/__init__.py
pycapsule/client/classification_nfb.py
pycapsule/client/classification_p300.py
pycapsule/client/client.py
pycapsule/client/remote_classifier.py
pycapsule/client/session.py
pycapsule/client/stimuli_player.py
pycapsule/mne/io.py
pycapsule/record_reader.py
pycapsule/types.py
pycapsule/utils.py
pycapsule-0.0.8.dist-info/WHEEL
pycapsule-0.0.8.dist-info/METADATA
pycapsule-0.0.8.dist-info/RECORD
