Metadata-Version: 2.1
Name: pycapsule
Version: 0.0.8
Summary: Various tools for Capsule BCI system
Author: Yaroslav Shmelev
Author-email: ysh@impulse-machine.com
Requires-Python: >=3.7,<4.0
Classifier: Programming Language :: Python :: 3
Classifier: Programming Language :: Python :: 3.7
Classifier: Programming Language :: Python :: 3.8
Classifier: Programming Language :: Python :: 3.9
Requires-Dist: msgpack (>=1.0.0,<2.0.0)
Requires-Dist: numpy (>=1.18.5,<2.0.0)
